stock_codes
