Metadata-Version: 1.0
Name: stock-codes
Version: 1.1
Summary: Analyze excel files to get codes
Home-page: https://github.com/Fedex75/stock_codes
Author: Federico Meza
Author-email: mezafabrello@gmail.com
License: MIT
Platform: UNKNOWN
